ascii_wizard/__init__.py
ascii_wizard-1.2.dist-info/METADATA
ascii_wizard-1.2.dist-info/WHEEL
ascii_wizard-1.2.dist-info/top_level.txt
ascii_wizard-1.2.dist-info/RECORD
