Metadata-Version: 2.1
Name: ascii-wizard
Version: 1.2
Summary: Convert images to ASCII representation
Home-page: https://github.com/IceWizard4902/ascii_wizard
Author: Nguyen Quang Vinh
Author-email: vinhnq4902@gmail.com
Project-URL: Bug Tracker, https://github.com/IceWizard4902/ascii_wizard/issues
Classifier: Programming Language :: Python :: 3
Classifier: License :: OSI Approved :: MIT License
Classifier: Operating System :: OS Independent
Requires-Python: >=3.7
Requires-Dist: Pillow
